README.md
setup.py
libmonzo/__init__.py
libmonzo/exceptions.py
libmonzo/monzo.py
libmonzo/types.py
libmonzo/utilities.py
libmonzo.egg-info/PKG-INFO
libmonzo.egg-info/SOURCES.txt
libmonzo.egg-info/dependency_links.txt
libmonzo.egg-info/top_level.txt