Metadata-Version: 2.1
Name: libmonzo
Version: 0.1
Summary: An API wrapper around Monzo bank accounts.
Home-page: https://github.com/dalemyers/libmonzo
Author: Dale Myers
Author-email: dale@myers.io
License: MIT
Keywords: bank,banks,monzo,mondo
Platform: UNKNOWN
Classifier: Development Status :: 3 - Alpha
Classifier: Intended Audience :: Developers
Classifier: Intended Audience :: Financial and Insurance Industry
Classifier: Intended Audience :: Information Technology
Classifier: License :: OSI Approved :: MIT License
Classifier: Programming Language :: Python :: 3
Classifier: Programming Language :: Python :: 3.7
Classifier: Topic :: Office/Business :: Financial
Classifier: Topic :: Software Development :: Libraries
